{
  "project_info": {
    "project_number": "964819859145",
    "firebase_url": "https://pawpal-2a62a.firebaseio.com",
    "project_id": "pawpal-2a62a",
    "storage_bucket": "pawpal-2a62a.appspot.com"
  },
  "client": [
    {
      "client_info": {
        "mobilesdk_app_id": "1:964819859145:android:22d4808a59163789",
        "android_client_info": {
          "package_name": "com.org.pawpal"
        }
      },
      "oauth_client": [
        {
          "client_id": "964819859145-csfeds2gqiu3s8mbs7i0i696vqp5oplu.apps.googleusercontent.com",
          "client_type": 3
        }
      ],
      "api_key": [
        {
          "current_key": "AIzaSyC126VyMoNFWT8qqiDpPvSOzmjoxMbrAH8"
        }
      ],
      "services": {
        "analytics_service": {
          "status": 1
        },
        "appinvite_service": {
          "status": 1,
          "other_platform_oauth_client": []
        },
        "ads_service": {
          "status": 2
        }
      }
    }
  ],
  "configuration_version": "1"
}